vinted_downloader/__init__.py
vinted_downloader/__main__.py
vinted_downloader-2.6.0.dist-info/licenses/LICENSE
vinted_downloader-2.6.0.dist-info/METADATA
vinted_downloader-2.6.0.dist-info/WHEEL
vinted_downloader-2.6.0.dist-info/entry_points.txt
vinted_downloader-2.6.0.dist-info/top_level.txt
vinted_downloader-2.6.0.dist-info/RECORD
