Metadata-Version: 2.4
Name: vinted-downloader
Version: 2.6.0
Summary: Download full size images and descriptions from Vinted
Author-email: Bruno Oberle <bruno@boberle.com>
Project-URL: Homepage, https://github.com/boberle/vinted-downloader
Project-URL: Issues, https://github.com/boberle/vinted-downloader/issues
Classifier: Programming Language :: Python :: 3
Classifier: License :: OSI Approved :: MIT License
Classifier: Operating System :: OS Independent
Requires-Python: >=3.8
License-File: LICENSE
Requires-Dist: requests
Dynamic: license-file
